<?xml version="1.0" encoding="utf-8"?>
<LanguageData>

  <!-- Counts masturbation -->

  <CountOfFappin.label>количество мастурбаций</CountOfFappin.label>
  <CountOfFappin.description>Количество моих мастурбаций.</CountOfFappin.description>


  <!-- Counts all sex -->

  <CountOfSex.label>количество секса</CountOfSex.label>
  <CountOfSex.description>Сколько секса у меня было.</CountOfSex.description>


  <!-- Counts all sex + rapes -->

  <CountOfSexWithHumanlikes.label>секса с людьми</CountOfSexWithHumanlikes.label>
  <CountOfSexWithHumanlikes.description>Количество секса с людьми.</CountOfSexWithHumanlikes.description>

  <CountOfSexWithAnimals.label>секса с животными</CountOfSexWithAnimals.label>
  <CountOfSexWithAnimals.description>Количество секса с животными.</CountOfSexWithAnimals.description>

  <CountOfSexWithInsects.label>секса с инсектами</CountOfSexWithInsects.label>
  <CountOfSexWithInsects.description>Количество секса с инсектами.</CountOfSexWithInsects.description>

  <CountOfSexWithOthers.label>секса с другими</CountOfSexWithOthers.label>
  <CountOfSexWithOthers.description>Количество секса со странными вещами.</CountOfSexWithOthers.description>

  <CountOfSexWithCorpse.label>секса с трупами</CountOfSexWithCorpse.label>
  <CountOfSexWithCorpse.description>Количество секса с трупами.</CountOfSexWithCorpse.description>


  <!-- Counts rapes -->

  <CountOfRapedHumanlikes.label>людей изнасиловано</CountOfRapedHumanlikes.label>
  <CountOfRapedHumanlikes.description>Сколько мной изнасиловано людей.</CountOfRapedHumanlikes.description>

  <CountOfRapedAnimals.label>животных изнасиловано</CountOfRapedAnimals.label>
  <CountOfRapedAnimals.description>Сколько мной изнасиловано животных.</CountOfRapedAnimals.description>

  <CountOfRapedInsects.label>инсектов изнасиловано</CountOfRapedInsects.label>
  <CountOfRapedInsects.description>Сколько мной изнасиловано инсектов.</CountOfRapedInsects.description>

  <CountOfRapedOthers.label>других изнасиловано</CountOfRapedOthers.label>
  <CountOfRapedOthers.description>Сколько мной изнасиловано других.</CountOfRapedOthers.description>

  <CountOfBeenRapedByHumanlikes.label>изнасилований от людей</CountOfBeenRapedByHumanlikes.label>
  <CountOfBeenRapedByHumanlikes.description>Сколько раз насиловали меня люди.</CountOfBeenRapedByHumanlikes.description>

  <CountOfBeenRapedByAnimals.label>изнасилований от животных</CountOfBeenRapedByAnimals.label>
  <CountOfBeenRapedByAnimals.description>Сколько раз насиловали меня животные.</CountOfBeenRapedByAnimals.description>

  <CountOfBeenRapedByInsects.label>изнасилований от инсектов</CountOfBeenRapedByInsects.label>
  <CountOfBeenRapedByInsects.description>Сколько раз насиловали меня инсекты.</CountOfBeenRapedByInsects.description>

  <CountOfBeenRapedByOthers.label>изнасилований от других</CountOfBeenRapedByOthers.label>
  <CountOfBeenRapedByOthers.description>Сколько раз насиловали меня другие.</CountOfBeenRapedByOthers.description>

  <GetRapedAsComfortPrisoner.label>изнасилований меня как ЗК</GetRapedAsComfortPrisoner.label>
  <GetRapedAsComfortPrisoner.description>Сколько раз насиловали меня для ЗК и колонистов.</GetRapedAsComfortPrisoner.description>


  <!-- Counts whore stuff -->

  <CountOfWhore.label>проституция</CountOfWhore.label>
  <CountOfWhore.description>Сколько раз я занимался протитуцией.</CountOfWhore.description>

  <EarnedMoneyByWhore.label>заработано серебра за проституцию</EarnedMoneyByWhore.label>
  <EarnedMoneyByWhore.description>Количество серебра, заработанное мной как шлюхой.</EarnedMoneyByWhore.description>


  <!-- Counts birthing -->

  <CountOfBirthHuman.label>рождено людей</CountOfBirthHuman.label>
  <CountOfBirthHuman.description>Сколько мной рождено людей.</CountOfBirthHuman.description>

  <CountOfBirthAnimal.label>рождено животных</CountOfBirthAnimal.label>
  <CountOfBirthAnimal.description>Сколько мной рождено животных.</CountOfBirthAnimal.description>

  <CountOfBirthEgg.label>рождено яиц</CountOfBirthEgg.label>
  <CountOfBirthEgg.description>Сколько мной рождено яиц.</CountOfBirthEgg.description>

  <CountOfCondomsUsed.label>использовано презервативов used</CountOfCondomsUsed.label>
  <CountOfCondomsUsed.description>Сколько мной использовано презервативов.</CountOfCondomsUsed.description>


</LanguageData>
